gdbundle_pycortexmdebug/__init__.py
gdbundle_pycortexmdebug/cmdebug/.git
gdbundle_pycortexmdebug/cmdebug/.gitignore
gdbundle_pycortexmdebug/cmdebug/LICENSE
gdbundle_pycortexmdebug/cmdebug/MANIFEST.in
gdbundle_pycortexmdebug/cmdebug/README.md
gdbundle_pycortexmdebug/cmdebug/cmdebug/__init__.py
gdbundle_pycortexmdebug/cmdebug/cmdebug/dwt_gdb.py
gdbundle_pycortexmdebug/cmdebug/cmdebug/svd.py
gdbundle_pycortexmdebug/cmdebug/cmdebug/svd_gdb.py
gdbundle_pycortexmdebug/cmdebug/scripts/gdb.py
gdbundle_pycortexmdebug/cmdebug/setup.py
gdbundle_pycortexmdebug/gdb_loader.py
gdbundle_pycortexmdebug-0.0.7.dist-info/WHEEL
gdbundle_pycortexmdebug-0.0.7.dist-info/METADATA
gdbundle_pycortexmdebug-0.0.7.dist-info/RECORD
